SISO/design.sv
// Code your design here
//SISO -> SERIAL INPUT SERIAL OUTPUT
//VAR1
/*module siso(input wire clk,input wire si,output wire so);
  
  reg [3:0] int_reg = 0;
  
  always @(posedge clk) 
  begin
    int_reg[0] <= si;
    int_reg[1] <= int_reg[0];
    int_reg[2] <= int_reg[1];
    int_reg[3] <= int_reg[2];
  end
  
  assign so = int_reg[3];
  
endmodule*/

//SHIFTARE LA  DREAPTA: si are cel mai putin semnificativ bit iar celelalte valori sunt shiftate spre dreapta, astfel încât int_reg[0] devine int_reg[1] etc
module siso(input wire clk,input wire reset,input wire si,output wire so);

  reg [3:0] int_reg = 0;

  always @(posedge clk or posedge reset) 
  begin
    if (reset)
      int_reg <= 4'b0000; //resetare pe 0
    else begin
      int_reg[0] <= si; //si este atribuit cu cel mai putin semnificativ bit
      int_reg[3:1] <= int_reg[2:0];//atribuie bitii 2->0 cu din reg bitului 3->1
      //int_reg <= {int_reg[2:0], si}; //concatenare: combina bitii 2->0 cu si
    end
  end

  assign so = int_reg[3]; //atribui so cu bitul cel mai putin semnificativ

endmodule

SISO/testbench.sv
// Code your testbench here
// or browse Examples
module tb_siso;

  reg clkt;
  reg resett;
  reg sit;
  wire sot;
  
  //instantierea
  siso siso_inst(.clk(clkt),.reset(resett),.si(sit),.so(sot));

  //Generarea semnalului de ceas
  initial
    begin
		#0 clkt = 1'b0;
		forever #5 clkt = ~clkt;
	end

  initial 
    begin
    resett = 1; sit = 0;
    #10 resett = 0; // Dezactivarea semnalului de reset după 10 unități de timp
    #20 sit = 1; // Setarea si la 1 după 20 unități de timp
    #20 sit = 0; // Setarea si la 0 după alte 20 unități de timp
    end
  
  initial 
    begin
    #100 $finish; // Terminarea simulării după 100 unități de timp
    end
  
  initial
    begin
      $dumpfile("dump.vcd");
      $dumpvars(0, siso_inst);
    end

endmodule

TEMA1/SISO/dump.vcd
$date
	Tue Jun 27 20:21:17 2023
$end
$version
	Icarus Verilog
$end
$timescale
	1s
$end
$scope module tb_siso $end
$scope module siso_inst $end
$var wire 1 ! clk $end
$var wire 1 " reset $end
$var wire 1 # si $end
$var wire 1 $ so $end
$var reg 4 % int_reg [3:0] $end
$upscope $end
$upscope $end
$enddefinitions $end
#0
$dumpvars
b0 %
0$
0#
1"
0!
$end
#5
1!
#10
0!
0"
#15
b0 %
1!
#20
0!
#25
b0 %
1!
#30
0!
1#
#35
b1 %
1!
#40
0!
#45
b11 %
1!
#50
0!
0#
#55
b110 %
1!
#60
0!
#65
1$
b1100 %
1!
#70
0!
#75
b1000 %
1!
#80
0!
#85
0$
b0 %
1!
#90
0!
#95
b0 %
1!
