SISO+SIPO+PISO+PIPO/design.sv
// Code your design here
//SISO -> SERIAL INPUT SERIAL OUTPUT
//SHIFTARE LA  DREAPTA: si are cel mai putin semnificativ bit iar celelalte valori sunt shiftate spre dreapta, astfel încât int_reg[0] devine int_reg[1] etc
module siso(input wire clk,input wire reset,input wire si,output wire so);

  reg [3:0] int_reg = 0;

  always @(posedge clk or posedge reset) 
  begin
    if (reset)
      int_reg <= 4'b0000; //resetare pe 0
    else begin
      int_reg[0] <= si; //si este atribuit cu cel mai putin semnificativ bit
      int_reg[3:1] <= int_reg[2:0];//atribuie bitii 2->0 cu din reg bitului 3->1
      //int_reg <= {int_reg[2:0], si}; //concatenare: combina bitii 2->0 cu si
    end
  end

  assign so = int_reg[3]; //atribui so cu bitul cel mai putin semnificativ

endmodule

//SIPO -> SERIAL INPUT PARALLEL OUTPUT
module sipo(input wire clk,input wire reset,input wire si,output reg[3:0] po);

  reg [3:0] int_reg = 0;

  always @(posedge clk or posedge reset) 
  begin
    if (reset)
      int_reg <= 4'b0000; //resetare pe 0
    else begin
      int_reg[0] <= si; //si este atribuit cu cel mai putin semnificativ bit
      int_reg[3:1] <= int_reg[2:0];//atribuie bitii 2->0 cu din reg bitului 3->1
      //int_reg <= {int_reg[2:0], si}; //concatenare: combina bitii 2->0 cu si =>preluat de la siso, nu are treaba :)
    end
  end

  always @(posedge clk) begin
    if (reset)
      po <= 4'b0000; //iesire paralela pe 0(initializare)
    else
      po <= int_reg; //iesirea paralela primeste valorile din int_reg
  end

endmodule

//PISO -> PARALLEL INPUT SERIAL OUTPUT
module piso(input wire clk,input wire reset, input wire mode,input wire pi,output reg so);
  
  reg [3:0] int_reg = 4'b0000;

  always @(posedge clk or posedge reset) 
    begin
      if (reset)
        int_reg <= 4'b0000; //stare initiala
      else if (mode == 1'b0)
        int_reg <= pi; //daca mode este 0  se va stoca valoarea din intrarea paralela in pi 
      else
        int_reg <= {int_reg[3], int_reg[3:1]}; //daca mode este 1 se va face shiftare la dreapta (bitul 3 se duce pe pozitia 2 si celelalte se muta la dreapta)
    end

  always @(posedge clk) 
    begin
      if (reset)
        so <= 1'b0; //resetare iesire
      else if (mode == 1'b1)
        so <= int_reg[0]; //daca mode e 1 so ia valoarea celui mai putin semnificativ bit
      else
        so <= 1'b0; //so ia valoarea logica 0
    end

endmodule

//PIPO -> PARLLEL INPUT PARALLEL OUTPUT 
//BUFFER REGISTER -> CE E LA INTRARE SE COPIAZA LA IESIRE
module pipo(input wire clk,input wire reset,input wire [3:0] pi,output reg [3:0] po);

  always @(posedge clk or posedge reset) 
    begin
      if (reset)
        po <= 4'b0000; //po este resetat
      else
        po <= pi; // po este egal cu intrarea paralela pi
    end
endmodule

SISO+SIPO+PISO+PIPO/testbench.sv
// Code your testbench here
// or browse Examples
module testbench;

  //declar toate semnalele
  reg clkt;
  reg resett;
  reg sit;
  wire sot;
  reg [3:0] pit;
  wire [3:0] pot;
  reg modet;

  //instantiere module
  siso siso_inst(.clk(clkt),.reset(resett),.si(sit),.so(sot));
  sipo sipo_inst (.clk(clkt),.reset(resett),.si(sit),.po(pot));
  piso piso_inst (.clk(clkt),.reset(resett),.pi(pit),.mode(modet),.so(sot));
  pipo pipo_inst (.clk(clkt),.reset(resett),.pi(pit),.po(pot));

  //Generarea semnalului de ceas
  initial
    begin
		#0 clkt = 1'b0;
		forever #5 clkt = ~clkt;
	end

  //intializare input
  initial begin
    resett = 1; sit = 0; pit = 0; modet = 0; //reset 1 e pentru o stare initiala a modulelor, si pe 0 si pi pe 0 pentru a testa functionalitatea modulelor cu valori de intrare, mode 0 pentru a incarca la piso
    #10 resett = 0; //resetare
    #20 sit = 1; // sit pe 1 
    #10 sit = 0; ///sit pe 0 
    #10 modet = 1; //shiftez 
    #20 modet = 0; //incarc
  end
  
  initial 
    begin
       #100 $finish; // Terminarea simulării după 100 unități de timp
    end
  
  initial
    begin
      $dumpfile("dump.vcd");
      $dumpvars(0, siso_inst);
      $dumpvars(0, sipo_inst);
      $dumpvars(0, piso_inst);
      $dumpvars(0, pipo_inst);
    end

endmodule

SISO+SIPO+PISO+PIPO/dump.vcd
$date
	Wed Jun 28 07:03:46 2023
$end
$version
	Icarus Verilog
$end
$timescale
	1s
$end
$scope module testbench $end
$scope module siso_inst $end
$var wire 1 ! clk $end
$var wire 1 " reset $end
$var wire 1 # si $end
$var wire 1 $ so $end
$var reg 4 % int_reg [3:0] $end
$upscope $end
$upscope $end
$scope module testbench $end
$scope module sipo_inst $end
$var wire 1 ! clk $end
$var wire 1 " reset $end
$var wire 1 # si $end
$var reg 4 & int_reg [3:0] $end
$var reg 4 ' po [3:0] $end
$upscope $end
$upscope $end
$scope module testbench $end
$scope module piso_inst $end
$var wire 1 ! clk $end
$var wire 1 ( mode $end
$var wire 1 ) pi $end
$var wire 1 " reset $end
$var reg 4 * int_reg [3:0] $end
$var reg 1 + so $end
$upscope $end
$upscope $end
$scope module testbench $end
$scope module pipo_inst $end
$var wire 1 ! clk $end
$var wire 4 , pi [3:0] $end
$var wire 1 " reset $end
$var reg 4 - po [3:0] $end
$upscope $end
$upscope $end
$enddefinitions $end
#0
$dumpvars
b0 -
b0 ,
x+
b0 *
0)
0(
bx '
b0 &
b0 %
x$
0#
1"
0!
$end
#5
b0 '
0+
0$
1!
#10
0!
0"
#15
b0 %
b0 &
1!
#20
0!
#25
b0 &
b0 %
1!
#30
0!
1#
#35
b1 %
b1 &
1!
#40
0!
0#
#45
b10 &
b10 %
b1 '
1!
#50
0!
1(
#55
b100 %
b100 &
b10 '
1!
#60
0!
#65
x$
b1000 &
b1000 %
b100 '
1!
#70
0!
0(
#75
0$
b0 %
b0 &
b1000 '
1!
#80
0!
#85
b0 &
b0 %
b0 '
1!
#90
0!
#95
b0 %
b0 &
1!
